{
  "skins": [
    {
      "localization_name": "Skin_653_0",
      "geometry": "geometry.humanoid.custom",
      "texture": "Skin_653_0.png",
      "type": "free"
    },
    {
      "localization_name": "Skin_653_1",
      "geometry": "geometry.humanoid.custom",
      "texture": "Skin_653_1.png",
      "type": "free"
    },
    {
      "localization_name": "Skin_653_2",
      "geometry": "geometry.humanoid.custom",
      "texture": "Skin_653_2.png",
      "type": "free"
    },
    {
      "localization_name": "Skin_653_3",
      "geometry": "geometry.humanoid.custom",
      "texture": "Skin_653_3.png",
      "type": "free"
    },
    {
      "localization_name": "Skin_653_4",
      "geometry": "geometry.humanoid.custom",
      "texture": "Skin_653_4.png",
      "type": "free"
    },
    {
      "localization_name": "Skin_653_5",
      "geometry": "geometry.humanoid.custom",
      "texture": "Skin_653_5.png",
      "type": "free"
    },
    {
      "localization_name": "Skin_653_6",
      "geometry": "geometry.humanoid.custom",
      "texture": "Skin_653_6.png",
      "type": "free"
    },
    {
      "localization_name": "Skin_653_7",
      "geometry": "geometry.humanoid.custom",
      "texture": "Skin_653_7.png",
      "type": "free"
    },
    {
      "localization_name": "Skin_653_8",
      "geometry": "geometry.humanoid.custom",
      "texture": "Skin_653_8.png",
      "type": "free"
    },
    {
      "localization_name": "Skin_653_9",
      "geometry": "geometry.humanoid.custom",
      "texture": "Skin_653_9.png",
      "type": "free"
    }
  ],
  "serialize_name": "Batch Pack",
  "localization_name": "Batch Pack"
}