{
  "skins": [
    {
      "localization_name": "MassSkin_00272_01",
      "geometry": "geometry.humanoid.custom",
      "texture": "MassSkin_00272_01.png",
      "type": "free"
    },
    {
      "localization_name": "MassSkin_00272_02",
      "geometry": "geometry.humanoid.custom",
      "texture": "MassSkin_00272_02.png",
      "type": "free"
    },
    {
      "localization_name": "MassSkin_00272_03",
      "geometry": "geometry.humanoid.custom",
      "texture": "MassSkin_00272_03.png",
      "type": "free"
    },
    {
      "localization_name": "MassSkin_00272_04",
      "geometry": "geometry.humanoid.custom",
      "texture": "MassSkin_00272_04.png",
      "type": "free"
    },
    {
      "localization_name": "MassSkin_00272_05",
      "geometry": "geometry.humanoid.custom",
      "texture": "MassSkin_00272_05.png",
      "type": "free"
    },
    {
      "localization_name": "MassSkin_00272_06",
      "geometry": "geometry.humanoid.custom",
      "texture": "MassSkin_00272_06.png",
      "type": "free"
    },
    {
      "localization_name": "MassSkin_00272_07",
      "geometry": "geometry.humanoid.custom",
      "texture": "MassSkin_00272_07.png",
      "type": "free"
    },
    {
      "localization_name": "MassSkin_00272_08",
      "geometry": "geometry.humanoid.custom",
      "texture": "MassSkin_00272_08.png",
      "type": "free"
    }
  ],
  "serialize_name": "Mass SunsetSafari #272",
  "localization_name": "Mass SunsetSafari #272"
}