{
  "skins": [
    {
      "localization_name": "Skin_509_0",
      "geometry": "geometry.humanoid.custom",
      "texture": "Skin_509_0.png",
      "type": "free"
    },
    {
      "localization_name": "Skin_509_1",
      "geometry": "geometry.humanoid.custom",
      "texture": "Skin_509_1.png",
      "type": "free"
    },
    {
      "localization_name": "Skin_509_2",
      "geometry": "geometry.humanoid.custom",
      "texture": "Skin_509_2.png",
      "type": "free"
    },
    {
      "localization_name": "Skin_509_3",
      "geometry": "geometry.humanoid.custom",
      "texture": "Skin_509_3.png",
      "type": "free"
    },
    {
      "localization_name": "Skin_509_4",
      "geometry": "geometry.humanoid.custom",
      "texture": "Skin_509_4.png",
      "type": "free"
    },
    {
      "localization_name": "Skin_509_5",
      "geometry": "geometry.humanoid.custom",
      "texture": "Skin_509_5.png",
      "type": "free"
    },
    {
      "localization_name": "Skin_509_6",
      "geometry": "geometry.humanoid.custom",
      "texture": "Skin_509_6.png",
      "type": "free"
    },
    {
      "localization_name": "Skin_509_7",
      "geometry": "geometry.humanoid.custom",
      "texture": "Skin_509_7.png",
      "type": "free"
    },
    {
      "localization_name": "Skin_509_8",
      "geometry": "geometry.humanoid.custom",
      "texture": "Skin_509_8.png",
      "type": "free"
    },
    {
      "localization_name": "Skin_509_9",
      "geometry": "geometry.humanoid.custom",
      "texture": "Skin_509_9.png",
      "type": "free"
    }
  ],
  "serialize_name": "Batch Pack",
  "localization_name": "Batch Pack"
}