{
  "skins": [
    {
      "localization_name": "MassSkin_00350_01",
      "geometry": "geometry.humanoid.custom",
      "texture": "MassSkin_00350_01.png",
      "type": "free"
    },
    {
      "localization_name": "MassSkin_00350_02",
      "geometry": "geometry.humanoid.custom",
      "texture": "MassSkin_00350_02.png",
      "type": "free"
    },
    {
      "localization_name": "MassSkin_00350_03",
      "geometry": "geometry.humanoid.custom",
      "texture": "MassSkin_00350_03.png",
      "type": "free"
    },
    {
      "localization_name": "MassSkin_00350_04",
      "geometry": "geometry.humanoid.custom",
      "texture": "MassSkin_00350_04.png",
      "type": "free"
    },
    {
      "localization_name": "MassSkin_00350_05",
      "geometry": "geometry.humanoid.custom",
      "texture": "MassSkin_00350_05.png",
      "type": "free"
    },
    {
      "localization_name": "MassSkin_00350_06",
      "geometry": "geometry.humanoid.custom",
      "texture": "MassSkin_00350_06.png",
      "type": "free"
    },
    {
      "localization_name": "MassSkin_00350_07",
      "geometry": "geometry.humanoid.custom",
      "texture": "MassSkin_00350_07.png",
      "type": "free"
    },
    {
      "localization_name": "MassSkin_00350_08",
      "geometry": "geometry.humanoid.custom",
      "texture": "MassSkin_00350_08.png",
      "type": "free"
    }
  ],
  "serialize_name": "Mass CandySummers #350",
  "localization_name": "Mass CandySummers #350"
}