{
  "skins": [
    {
      "localization_name": "MassSkin_00702_01",
      "geometry": "geometry.humanoid.custom",
      "texture": "MassSkin_00702_01.png",
      "type": "free"
    },
    {
      "localization_name": "MassSkin_00702_02",
      "geometry": "geometry.humanoid.custom",
      "texture": "MassSkin_00702_02.png",
      "type": "free"
    },
    {
      "localization_name": "MassSkin_00702_03",
      "geometry": "geometry.humanoid.custom",
      "texture": "MassSkin_00702_03.png",
      "type": "free"
    },
    {
      "localization_name": "MassSkin_00702_04",
      "geometry": "geometry.humanoid.custom",
      "texture": "MassSkin_00702_04.png",
      "type": "free"
    },
    {
      "localization_name": "MassSkin_00702_05",
      "geometry": "geometry.humanoid.custom",
      "texture": "MassSkin_00702_05.png",
      "type": "free"
    },
    {
      "localization_name": "MassSkin_00702_06",
      "geometry": "geometry.humanoid.custom",
      "texture": "MassSkin_00702_06.png",
      "type": "free"
    },
    {
      "localization_name": "MassSkin_00702_07",
      "geometry": "geometry.humanoid.custom",
      "texture": "MassSkin_00702_07.png",
      "type": "free"
    },
    {
      "localization_name": "MassSkin_00702_08",
      "geometry": "geometry.humanoid.custom",
      "texture": "MassSkin_00702_08.png",
      "type": "free"
    }
  ],
  "serialize_name": "Mass SakuraGarden #702",
  "localization_name": "Mass SakuraGarden #702"
}