{
  "skins": [
    {
      "localization_name": "MassSkin_00920_01",
      "geometry": "geometry.humanoid.custom",
      "texture": "MassSkin_00920_01.png",
      "type": "free"
    },
    {
      "localization_name": "MassSkin_00920_02",
      "geometry": "geometry.humanoid.custom",
      "texture": "MassSkin_00920_02.png",
      "type": "free"
    },
    {
      "localization_name": "MassSkin_00920_03",
      "geometry": "geometry.humanoid.custom",
      "texture": "MassSkin_00920_03.png",
      "type": "free"
    },
    {
      "localization_name": "MassSkin_00920_04",
      "geometry": "geometry.humanoid.custom",
      "texture": "MassSkin_00920_04.png",
      "type": "free"
    },
    {
      "localization_name": "MassSkin_00920_05",
      "geometry": "geometry.humanoid.custom",
      "texture": "MassSkin_00920_05.png",
      "type": "free"
    },
    {
      "localization_name": "MassSkin_00920_06",
      "geometry": "geometry.humanoid.custom",
      "texture": "MassSkin_00920_06.png",
      "type": "free"
    },
    {
      "localization_name": "MassSkin_00920_07",
      "geometry": "geometry.humanoid.custom",
      "texture": "MassSkin_00920_07.png",
      "type": "free"
    },
    {
      "localization_name": "MassSkin_00920_08",
      "geometry": "geometry.humanoid.custom",
      "texture": "MassSkin_00920_08.png",
      "type": "free"
    }
  ],
  "serialize_name": "Mass CandySummers #920",
  "localization_name": "Mass CandySummers #920"
}