{
  "skins": [
    {
      "localization_name": "MassSkin_00492_01",
      "geometry": "geometry.humanoid.custom",
      "texture": "MassSkin_00492_01.png",
      "type": "free"
    },
    {
      "localization_name": "MassSkin_00492_02",
      "geometry": "geometry.humanoid.custom",
      "texture": "MassSkin_00492_02.png",
      "type": "free"
    },
    {
      "localization_name": "MassSkin_00492_03",
      "geometry": "geometry.humanoid.custom",
      "texture": "MassSkin_00492_03.png",
      "type": "free"
    },
    {
      "localization_name": "MassSkin_00492_04",
      "geometry": "geometry.humanoid.custom",
      "texture": "MassSkin_00492_04.png",
      "type": "free"
    },
    {
      "localization_name": "MassSkin_00492_05",
      "geometry": "geometry.humanoid.custom",
      "texture": "MassSkin_00492_05.png",
      "type": "free"
    },
    {
      "localization_name": "MassSkin_00492_06",
      "geometry": "geometry.humanoid.custom",
      "texture": "MassSkin_00492_06.png",
      "type": "free"
    },
    {
      "localization_name": "MassSkin_00492_07",
      "geometry": "geometry.humanoid.custom",
      "texture": "MassSkin_00492_07.png",
      "type": "free"
    },
    {
      "localization_name": "MassSkin_00492_08",
      "geometry": "geometry.humanoid.custom",
      "texture": "MassSkin_00492_08.png",
      "type": "free"
    }
  ],
  "serialize_name": "Mass SakuraGarden #492",
  "localization_name": "Mass SakuraGarden #492"
}