{
  "skins": [
    {
      "localization_name": "MassSkin_00906_01",
      "geometry": "geometry.humanoid.custom",
      "texture": "MassSkin_00906_01.png",
      "type": "free"
    },
    {
      "localization_name": "MassSkin_00906_02",
      "geometry": "geometry.humanoid.custom",
      "texture": "MassSkin_00906_02.png",
      "type": "free"
    },
    {
      "localization_name": "MassSkin_00906_03",
      "geometry": "geometry.humanoid.custom",
      "texture": "MassSkin_00906_03.png",
      "type": "free"
    },
    {
      "localization_name": "MassSkin_00906_04",
      "geometry": "geometry.humanoid.custom",
      "texture": "MassSkin_00906_04.png",
      "type": "free"
    },
    {
      "localization_name": "MassSkin_00906_05",
      "geometry": "geometry.humanoid.custom",
      "texture": "MassSkin_00906_05.png",
      "type": "free"
    },
    {
      "localization_name": "MassSkin_00906_06",
      "geometry": "geometry.humanoid.custom",
      "texture": "MassSkin_00906_06.png",
      "type": "free"
    },
    {
      "localization_name": "MassSkin_00906_07",
      "geometry": "geometry.humanoid.custom",
      "texture": "MassSkin_00906_07.png",
      "type": "free"
    },
    {
      "localization_name": "MassSkin_00906_08",
      "geometry": "geometry.humanoid.custom",
      "texture": "MassSkin_00906_08.png",
      "type": "free"
    }
  ],
  "serialize_name": "Mass OceanDepths #906",
  "localization_name": "Mass OceanDepths #906"
}